ocraft/__init__.py
ocraft/cli/__init__.py
ocraft/cli/app.py
ocraft-0.0.1.dist-info/METADATA
ocraft-0.0.1.dist-info/WHEEL
ocraft-0.0.1.dist-info/entry_points.txt
ocraft-0.0.1.dist-info/RECORD
