Metadata-Version: 2.1
Name: ocraft
Version: 0.0.1
Summary: It reads "Oh! Craft". This is package for OCR.
Author: isaac-fei
Author-email: isaac.omega.fei@gmail.com
Requires-Python: >=3.11,<4.0
Classifier: Programming Language :: Python :: 3
Classifier: Programming Language :: Python :: 3.11
Requires-Dist: typer[all] (>=0.9.0,<0.10.0)
